rakam_analytics/__init__.py
rakam_analytics/decorators.py
rakam_analytics/loggers.py
rakam_analytics-0.0.7.dist-info/LICENSE
rakam_analytics-0.0.7.dist-info/METADATA
rakam_analytics-0.0.7.dist-info/WHEEL
rakam_analytics-0.0.7.dist-info/top_level.txt
rakam_analytics-0.0.7.dist-info/RECORD
