Metadata-Version: 2.1
Name: rakam_analytics
Version: 0.0.7
Summary: A package to gather analytics on rakam projects
Author-email: Rakam <clement@rakam.ai>
Project-URL: Homepage, https://gitlab.com/rakam-ai-services/internal-tech/rakam-analytics-package
Keywords: rakam,django
Classifier: Programming Language :: Python
Classifier: Programming Language :: Python :: 3
Classifier: License :: OSI Approved :: MIT License
Classifier: Operating System :: OS Independent
Classifier: Intended Audience :: Developers
Requires-Python: >=3.8
License-File: LICENSE
